{
  "nm": "2",
  "ddd": 0,
  "h": 24,
  "w": 24,
  "meta": {"g": "@lottiefiles/toolkit-js 0.33.2"},
  "layers": [
    {
      "ty": 4,
      "nm": "Grey D",
      "sr": 1,
      "st": 0,
      "op": 123,
      "ip": 0,
      "hd": false,
      "ddd": 0,
      "bm": 0,
      "hasMask": false,
      "ao": 0,
      "ks": {
        "a": {"a": 0, "k": [4.086, -13.25, 0]},
        "s": {"a": 0, "k": [100, 100, 100]},
        "sk": {"a": 0, "k": 0},
        "p": {"a": 0, "k": [12, 4.5, 0]},
        "r": {
          "a": 1,
          "k": [
            {
              "o": {"x": 0.167, "y": 0.167},
              "i": {"x": 0.833, "y": 0.833},
              "s": [0],
              "t": 25
            },
            {
              "o": {"x": 0.167, "y": 0.167},
              "i": {"x": 0.833, "y": 0.833},
              "s": [6],
              "t": 28
            },
            {
              "o": {"x": 0.167, "y": 0.167},
              "i": {"x": 0.833, "y": 0.833},
              "s": [-26],
              "t": 36
            },
            {"s": [0], "t": 45}
          ]
        },
        "sa": {"a": 0, "k": 0},
        "o": {"a": 0, "k": 100}
      },
      "ef": [],
      "shapes": [
        {
          "ty": "gr",
          "bm": 0,
          "hd": false,
          "nm": "G",
          "it": [
            {
              "ty": "sh",
              "bm": 0,
              "hd": false,
              "nm": "P",
              "d": 1,
              "ks": {
                "a": 0,
                "k": {
                  "c": true,
                  "i": [
                    [0.135, 0],
                    [0, 0],
                    [-0.043, -0.129],
                    [-1.764, 0],
                    [-0.525, 1.594]
                  ],
                  "o": [
                    [0, 0],
                    [-0.135, 0],
                    [0.525, 1.594],
                    [1.765, 0],
                    [0.042, -0.129]
                  ],
                  "v": [
                    [3.598, -1.5],
                    [-3.597, -1.5],
                    [-3.793, -1.237],
                    [0, 1.5],
                    [3.794, -1.237]
                  ]
                }
              }
            },
            {
              "ty": "sh",
              "bm": 0,
              "hd": false,
              "nm": "P",
              "d": 1,
              "ks": {
                "a": 0,
                "k": {
                  "c": true,
                  "i": [
                    [0, 0],
                    [0.877, 0],
                    [0.555, 0.623]
                  ],
                  "o": [
                    [-0.555, 0.623],
                    [-0.877, 0],
                    [0, 0]
                  ],
                  "v": [
                    [2.239, -0.5],
                    [0, 0.5],
                    [-2.238, -0.5]
                  ]
                }
              }
            },
            {"ty": "mm", "bm": 0, "hd": false, "nm": "M", "mm": 1},
            {
              "ty": "fl",
              "bm": 0,
              "hd": false,
              "nm": "F",
              "c": {
                "a": 1,
                "k": [
                  {
                    "o": {"x": 0.167, "y": 0.167},
                    "i": {"x": 0.833, "y": 0.833},
                    "s": [0.6667, 0.6667, 0.6667],
                    "t": 22
                  },
                  {"s": [0.9059, 0.4471, 0.2157], "t": 39}
                ]
              },
              "r": 1,
              "o": {"a": 0, "k": 100}
            },
            {
              "ty": "tr",
              "a": {"a": 0, "k": [0, 0.5]},
              "s": {"a": 0, "k": [100, 100]},
              "sk": {"a": 0, "k": 0},
              "p": {"a": 0, "k": [4.086, 2.25]},
              "r": {"a": 0, "k": 0},
              "sa": {"a": 0, "k": 0},
              "o": {"a": 0, "k": 100}
            }
          ]
        },
        {
          "ty": "st",
          "bm": 0,
          "hd": false,
          "nm": "Stroke",
          "lc": 2,
          "lj": 2,
          "ml": 1,
          "o": {"a": 0, "k": 100},
          "w": {"a": 0, "k": 0.1},
          "c": {
            "a": 1,
            "k": [
              {
                "o": {"x": 0.167, "y": 0.167},
                "i": {"x": 0.833, "y": 0.833},
                "s": [0.6667, 0.6667, 0.6667],
                "t": 22
              },
              {"s": [0.9059, 0.4471, 0.2157], "t": 39}
            ]
          }
        }
      ],
      "ind": 1
    },
    {
      "ty": 4,
      "nm": "Grey T",
      "sr": 1,
      "st": 0,
      "op": 125,
      "ip": 0,
      "hd": false,
      "ddd": 0,
      "bm": 0,
      "hasMask": false,
      "ao": 0,
      "ks": {
        "a": {"a": 0, "k": [7.811, 0.25, 0]},
        "s": {"a": 0, "k": [100, 100, 100]},
        "sk": {"a": 0, "k": 0},
        "p": {"a": 0, "k": [12, 3, 0]},
        "r": {
          "a": 1,
          "k": [
            {"o": {"x": 0, "y": 0}, "i": {"x": 0, "y": 1}, "s": [0], "t": 25},
            {"o": {"x": 0, "y": 0}, "i": {"x": 0, "y": 1}, "s": [5], "t": 28},
            {
              "o": {"x": 0.729, "y": 0},
              "i": {"x": 0.688, "y": 1},
              "s": [-15],
              "t": 36
            },
            {
              "o": {"x": 0.167, "y": 0},
              "i": {"x": 0.833, "y": 1},
              "s": [6],
              "t": 45
            },
            {
              "o": {"x": 0.167, "y": 0},
              "i": {"x": 0.833, "y": 1},
              "s": [-3],
              "t": 48
            },
            {"s": [0], "t": 55}
          ]
        },
        "sa": {"a": 0, "k": 0},
        "o": {"a": 0, "k": 100}
      },
      "ef": [],
      "shapes": [
        {
          "ty": "gr",
          "bm": 0,
          "hd": false,
          "nm": "G",
          "it": [
            {
              "ty": "sh",
              "bm": 0,
              "hd": false,
              "nm": "P",
              "d": 1,
              "ks": {
                "a": 0,
                "k": {
                  "c": true,
                  "i": [
                    [3.748, 0],
                    [0, -3.149],
                    [0, 0],
                    [0.063, -0.347],
                    [0.518, -0.906],
                    [0.269, -0.345],
                    [-0.414, 0],
                    [0, 0],
                    [0, 0],
                    [0.255, 0.327],
                    [0.261, 0.456],
                    [0.115, 0.633],
                    [0, 0.352],
                    [0, 0]
                  ],
                  "o": [
                    [-3.751, 0],
                    [0, 0],
                    [0, 0.352],
                    [-0.115, 0.633],
                    [-0.26, 0.456],
                    [-0.256, 0.327],
                    [0, 0],
                    [0, 0],
                    [0.415, 0],
                    [-0.27, -0.345],
                    [-0.518, -0.906],
                    [-0.063, -0.347],
                    [0, 0],
                    [0, -3.149]
                  ],
                  "v": [
                    [0, -7.062],
                    [-5.625, -1.182],
                    [-5.625, 1.771],
                    [-5.719, 2.82],
                    [-6.5, 5.062],
                    [-7.305, 6.262],
                    [-6.909, 7.062],
                    [0, 7.062],
                    [6.908, 7.062],
                    [7.306, 6.262],
                    [6.5, 5.062],
                    [5.719, 2.82],
                    [5.625, 1.771],
                    [5.625, -1.182]
                  ]
                }
              }
            },
            {
              "ty": "sh",
              "bm": 0,
              "hd": false,
              "nm": "P",
              "d": 1,
              "ks": {
                "a": 0,
                "k": {
                  "c": true,
                  "i": [
                    [-3.41, 0],
                    [0, -2.359],
                    [0, 0],
                    [-0.073, -0.402],
                    [-0.583, -1.021],
                    [-0.106, -0.166],
                    [0, 0],
                    [0, 0],
                    [-0.098, 0.17],
                    [-0.134, 0.735],
                    [0, 0.413],
                    [0, 0]
                  ],
                  "o": [
                    [3.41, 0],
                    [0, 0],
                    [0, 0.413],
                    [0.134, 0.735],
                    [0.097, 0.17],
                    [0, 0],
                    [0, 0],
                    [0.106, -0.166],
                    [0.583, -1.021],
                    [0.073, -0.402],
                    [0, 0],
                    [0, -2.359]
                  ],
                  "v": [
                    [0, -6.062],
                    [4.625, -1.182],
                    [4.625, 1.771],
                    [4.735, 2.999],
                    [5.632, 5.559],
                    [5.937, 6.062],
                    [0, 6.062],
                    [-5.937, 6.062],
                    [-5.631, 5.559],
                    [-4.735, 2.999],
                    [-4.625, 1.771],
                    [-4.625, -1.182]
                  ]
                }
              }
            },
            {"ty": "mm", "bm": 0, "hd": false, "nm": "M", "mm": 1},
            {
              "ty": "fl",
              "bm": 0,
              "hd": false,
              "nm": "F",
              "c": {
                "a": 1,
                "k": [
                  {
                    "o": {"x": 0.167, "y": 0.167},
                    "i": {"x": 0.833, "y": 0.833},
                    "s": [0.6667, 0.6667, 0.6667],
                    "t": 23
                  },
                  {"s": [0.9059, 0.4471, 0.2157], "t": 39}
                ]
              },
              "r": 1,
              "o": {"a": 0, "k": 100}
            },
            {
              "ty": "tr",
              "a": {"a": 0, "k": [0, 0]},
              "s": {"a": 0, "k": [100, 100]},
              "sk": {"a": 0, "k": 0},
              "p": {"a": 0, "k": [7.811, 7.312]},
              "r": {"a": 0, "k": 0},
              "sa": {"a": 0, "k": 0},
              "o": {"a": 0, "k": 100}
            }
          ]
        },
        {
          "ty": "st",
          "bm": 0,
          "hd": false,
          "nm": "Stroke",
          "lc": 2,
          "lj": 2,
          "ml": 1,
          "o": {"a": 0, "k": 100},
          "w": {"a": 0, "k": 0.4},
          "c": {
            "a": 1,
            "k": [
              {
                "o": {"x": 0.167, "y": 0.167},
                "i": {"x": 0.833, "y": 0.833},
                "s": [0.6667, 0.6667, 0.6667],
                "t": 23
              },
              {"s": [0.9059, 0.4471, 0.2157], "t": 39}
            ]
          }
        }
      ],
      "ind": 2
    },
    {
      "ty": 4,
      "nm": "L",
      "sr": 1,
      "st": 0,
      "op": 126,
      "ip": 0,
      "hd": false,
      "ddd": 0,
      "bm": 0,
      "hasMask": false,
      "ao": 0,
      "ks": {
        "a": {"a": 0, "k": [4.086, -13.25, 0]},
        "s": {"a": 0, "k": [100, 100, 100]},
        "sk": {"a": 0, "k": 0},
        "p": {"a": 0, "k": [12, 4.5, 0]},
        "r": {
          "a": 1,
          "k": [
            {
              "o": {"x": 0.167, "y": 0.167},
              "i": {"x": 0.833, "y": 0.833},
              "s": [-26],
              "t": 36
            },
            {
              "o": {"x": 0.167, "y": 0.167},
              "i": {"x": 0.833, "y": 0.833},
              "s": [6],
              "t": 45
            },
            {"s": [0], "t": 55}
          ]
        },
        "sa": {"a": 0, "k": 0},
        "o": {
          "a": 1,
          "k": [
            {
              "o": {"x": 1, "y": 0},
              "i": {"x": 0.667, "y": 1},
              "s": [0],
              "t": 27
            },
            {
              "o": {"x": 0.167, "y": 0},
              "i": {"x": 0.833, "y": 1},
              "s": [100],
              "t": 36
            },
            {
              "o": {"x": 0.167, "y": 0},
              "i": {"x": 0.833, "y": 1},
              "s": [100],
              "t": 100
            },
            {"s": [1], "t": 107}
          ]
        }
      },
      "ef": [],
      "shapes": [
        {
          "ty": "gr",
          "bm": 0,
          "hd": false,
          "nm": "G",
          "it": [
            {
              "ty": "sh",
              "bm": 0,
              "hd": false,
              "nm": "P",
              "d": 1,
              "ks": {
                "a": 0,
                "k": {
                  "c": true,
                  "i": [
                    [0, 0],
                    [0.042, -0.129],
                    [1.765, 0],
                    [0.525, 1.594],
                    [-0.135, 0]
                  ],
                  "o": [
                    [0.135, 0],
                    [-0.525, 1.594],
                    [-1.764, 0],
                    [-0.043, -0.129],
                    [0, 0]
                  ],
                  "v": [
                    [3.598, -1.5],
                    [3.794, -1.237],
                    [0, 1.5],
                    [-3.793, -1.237],
                    [-3.597, -1.5]
                  ]
                }
              }
            },
            {
              "ty": "fl",
              "bm": 0,
              "hd": false,
              "nm": "F",
              "c": {"a": 0, "k": [1, 0.8588, 0.7882]},
              "r": 1,
              "o": {"a": 0, "k": 100}
            },
            {
              "ty": "tr",
              "a": {"a": 0, "k": [0, 0.5]},
              "s": {"a": 0, "k": [100, 100]},
              "sk": {"a": 0, "k": 0},
              "p": {"a": 0, "k": [4.086, 2.25]},
              "r": {"a": 0, "k": 0},
              "sa": {"a": 0, "k": 0},
              "o": {"a": 0, "k": 100}
            }
          ]
        },
        {
          "ty": "st",
          "bm": 0,
          "hd": false,
          "nm": "Stroke",
          "lc": 2,
          "lj": 2,
          "ml": 1,
          "o": {"a": 0, "k": 100},
          "w": {"a": 0, "k": 0.5},
          "c": {"a": 0, "k": [1, 0.8588, 0.7882]}
        }
      ],
      "ind": 3
    },
    {
      "ty": 4,
      "nm": "L",
      "sr": 1,
      "st": 0,
      "op": 124,
      "ip": 0,
      "hd": false,
      "ddd": 0,
      "bm": 0,
      "hasMask": false,
      "ao": 0,
      "ks": {
        "a": {"a": 0, "k": [7.811, 0.25, 0]},
        "s": {"a": 0, "k": [100, 100, 100]},
        "sk": {"a": 0, "k": 0},
        "p": {"a": 0, "k": [12, 3, 0]},
        "r": {
          "a": 1,
          "k": [
            {
              "o": {"x": 0.729, "y": 0},
              "i": {"x": 0.688, "y": 1},
              "s": [-15],
              "t": 36
            },
            {
              "o": {"x": 0.167, "y": 0},
              "i": {"x": 0.833, "y": 1},
              "s": [6],
              "t": 45
            },
            {
              "o": {"x": 0.167, "y": 0},
              "i": {"x": 0.833, "y": 1},
              "s": [-3],
              "t": 48
            },
            {"s": [0], "t": 55}
          ]
        },
        "sa": {"a": 0, "k": 0},
        "o": {
          "a": 1,
          "k": [
            {
              "o": {"x": 1, "y": 0},
              "i": {"x": 0.667, "y": 1},
              "s": [0],
              "t": 27
            },
            {
              "o": {"x": 0.167, "y": 0},
              "i": {"x": 0.833, "y": 1},
              "s": [100],
              "t": 36
            },
            {
              "o": {"x": 0.167, "y": 0},
              "i": {"x": 0.833, "y": 1},
              "s": [100],
              "t": 100
            },
            {"s": [0], "t": 107}
          ]
        }
      },
      "ef": [],
      "shapes": [
        {
          "ty": "gr",
          "bm": 0,
          "hd": false,
          "nm": "G",
          "it": [
            {
              "ty": "sh",
              "bm": 0,
              "hd": false,
              "nm": "P",
              "d": 1,
              "ks": {
                "a": 0,
                "k": {
                  "c": true,
                  "i": [
                    [0.261, 0.456],
                    [0.115, 0.633],
                    [0, 0.352],
                    [0, 0],
                    [3.748, 0],
                    [0, -3.149],
                    [0, 0],
                    [0.063, -0.347],
                    [0.517, -0.906],
                    [0.269, -0.345],
                    [-0.414, 0],
                    [0, 0],
                    [0, 0],
                    [0.255, 0.327]
                  ],
                  "o": [
                    [-0.518, -0.906],
                    [-0.063, -0.347],
                    [0, 0],
                    [0, -3.149],
                    [-3.751, 0],
                    [0, 0],
                    [0, 0.352],
                    [-0.115, 0.633],
                    [-0.26, 0.456],
                    [-0.256, 0.327],
                    [0, 0],
                    [0, 0],
                    [0.415, 0],
                    [-0.27, -0.345]
                  ],
                  "v": [
                    [6.5, 5.062],
                    [5.719, 2.82],
                    [5.625, 1.771],
                    [5.625, -1.182],
                    [0, -7.062],
                    [-5.625, -1.182],
                    [-5.625, 1.771],
                    [-5.719, 2.82],
                    [-6.5, 5.062],
                    [-7.305, 6.262],
                    [-6.909, 7.062],
                    [0, 7.062],
                    [6.908, 7.062],
                    [7.306, 6.262]
                  ]
                }
              }
            },
            {
              "ty": "fl",
              "bm": 0,
              "hd": false,
              "nm": "F",
              "c": {"a": 0, "k": [1, 0.8588, 0.7882]},
              "r": 1,
              "o": {"a": 0, "k": 100}
            },
            {
              "ty": "tr",
              "a": {"a": 0, "k": [0, -0.062000000000001165]},
              "s": {"a": 0, "k": [100, 100]},
              "sk": {"a": 0, "k": 0},
              "p": {"a": 0, "k": [7.811, 7.249999999999999]},
              "r": {"a": 0, "k": 0},
              "sa": {"a": 0, "k": 0},
              "o": {"a": 0, "k": 100}
            }
          ]
        }
      ],
      "ind": 4
    }
  ],
  "v": "4.8.0",
  "fr": 25,
  "op": 75,
  "ip": 0,
  "assets": []
}
